airflow_orjson_serialization/__init__.py
airflow_orjson_serialization/cli.py
airflow_orjson_serialization/json.py
airflow_orjson_serialization-0.1.0.dist-info/METADATA
airflow_orjson_serialization-0.1.0.dist-info/WHEEL
airflow_orjson_serialization-0.1.0.dist-info/entry_points.txt
airflow_orjson_serialization-0.1.0.dist-info/top_level.txt
airflow_orjson_serialization-0.1.0.dist-info/RECORD
