Metadata-Version: 2.4
Name: airflow-orjson-serialization
Version: 0.1.0
Summary: A orjson wrapper for use in Apache Airflow
Author-email: Yuntae Park <tnqkr4610@gmail.com>
Requires-Python: >=3.9
Requires-Dist: jinja2>=3.1.6
Requires-Dist: orjson>=3.10.16
Provides-Extra: test
Requires-Dist: pytest; extra == "test"
